friendlyshell/__init__.py
friendlyshell/base_shell.py
friendlyshell/basic_logger_mixin.py
friendlyshell/basic_shell.py
friendlyshell/command_complete_mixin.py
friendlyshell/command_parsers.py
friendlyshell/shell_help_mixin.py
friendlyshell/version.py
friendlyshell-1.0.9.dist-info/DESCRIPTION.rst
friendlyshell-1.0.9.dist-info/METADATA
friendlyshell-1.0.9.dist-info/RECORD
friendlyshell-1.0.9.dist-info/WHEEL
friendlyshell-1.0.9.dist-info/entry_points.txt
friendlyshell-1.0.9.dist-info/metadata.json
friendlyshell-1.0.9.dist-info/top_level.txt
