Metadata-Version: 2.0
Name: friendlyshell
Version: 1.0.9
Summary: Framework for writing interactive Python command line interfaces, similar to the 'cmd' built in class.
Home-page: https://github.com/TheFriendlyCoder/friendlyshell
Author: Kevin S. Phillips
Author-email: thefriendlycoder@gmail.com
License: Apache License 2.0
Keywords: cmd command line shell interactive interpreter
Platform: UNKNOWN
Classifier: Development Status :: 3 - Alpha
Classifier: Environment :: Console
Classifier: License :: OSI Approved :: Apache Software License
Classifier: Topic :: Software Development :: Libraries
Classifier: Natural Language :: English
Classifier: Operating System :: OS Independent
Classifier: Programming Language :: Python :: 2
Classifier: Programming Language :: Python :: 3
Requires-Python: >=2.7, !=3.0.*, !=3.1.*, !=3.2.*, !=3.3.*, <4
Requires-Dist: six
Requires-Dist: pyparsing
Requires-Dist: tabulate
Requires-Dist: pyreadline; platform_system == "Windows"
Provides-Extra: dev
Requires-Dist: twine; extra == 'dev'
Requires-Dist: pytest; extra == 'dev'
Requires-Dist: pytest-cov; extra == 'dev'
Requires-Dist: pytest-timeout; extra == 'dev'
Requires-Dist: mock; extra == 'dev'
Requires-Dist: pylint; extra == 'dev'
Requires-Dist: sphinx; extra == 'dev'
Requires-Dist: tox; extra == 'dev'
